{
  "timestamp": "2026-06-13T19:16:58.155Z",
  "project": "trccyyalqgsjkuszaqhr",
  "data": {
    "profiles": [],
    "dining_tables": [],
    "reservations": [],
    "reservation_status_events": [],
    "categories": [],
    "menu_items": [],
    "service_hours": [
      {
        "id": "4b6e9484-a60d-43cb-8466-ae76a91a7519",
        "service_type": "dine_in",
        "day_of_week": 0,
        "slot_number": 1,
        "open_time": "12:00:00",
        "close_time": "22:00:00",
        "is_closed": false,
        "min_lead_time_minutes": 0,
        "max_preorder_days": 0,
        "last_order_time": null,
        "display_order": 1,
        "created_at": "2026-06-13T19:12:52.953Z",
        "updated_at": "2026-06-13T19:12:52.953Z",
        "updated_by": null
      },
      {
        "id": "4792d581-80bd-4f1a-abfa-f4215e0c2db5",
        "service_type": "reservations",
        "day_of_week": 0,
        "slot_number": 1,
        "open_time": "12:00:00",
        "close_time": "21:00:00",
        "is_closed": false,
        "min_lead_time_minutes": 30,
        "max_preorder_days": 30,
        "last_order_time": null,
        "display_order": 2,
        "created_at": "2026-06-13T19:12:52.953Z",
        "updated_at": "2026-06-13T19:12:52.953Z",
        "updated_by": null
      },
      {
        "id": "63891cfc-49a2-4469-b0aa-7a47424fa4a3",
        "service_type": "delivery",
        "day_of_week": 0,
        "slot_number": 1,
        "open_time": "12:00:00",
        "close_time": "21:30:00",
        "is_closed": false,
        "min_lead_time_minutes": 45,
        "max_preorder_days": 7,
        "last_order_time": null,
        "display_order": 3,
        "created_at": "2026-06-13T19:12:52.953Z",
        "updated_at": "2026-06-13T19:12:52.953Z",
        "updated_by": null
      },
      {
        "id": "0172a4de-e844-4184-b92b-597f3458d1c4",
        "service_type": "takeaway",
        "day_of_week": 0,
        "slot_number": 1,
        "open_time": "12:00:00",
        "close_time": "21:45:00",
        "is_closed": false,
        "min_lead_time_minutes": 15,
        "max_preorder_days": 7,
        "last_order_time": null,
        "display_order": 4,
        "created_at": "2026-06-13T19:12:52.953Z",
        "updated_at": "2026-06-13T19:12:52.953Z",
        "updated_by": null
      },
      {
        "id": "149861e3-6ea9-4d2f-8ac3-f5868cecf42b",
        "service_type": "reservations",
        "day_of_week": 1,
        "slot_number": 1,
        "open_time": "12:00:00",
        "close_time": "21:00:00",
        "is_closed": false,
        "min_lead_time_minutes": 30,
        "max_preorder_days": 30,
        "last_order_time": null,
        "display_order": 2,
        "created_at": "2026-06-13T19:12:52.953Z",
        "updated_at": "2026-06-13T19:12:52.953Z",
        "updated_by": null
      },
      {
        "id": "b46254fb-126e-48c1-811a-043a7ccec7ea",
        "service_type": "delivery",
        "day_of_week": 1,
        "slot_number": 1,
        "open_time": "12:00:00",
        "close_time": "21:30:00",
        "is_closed": false,
        "min_lead_time_minutes": 45,
        "max_preorder_days": 7,
        "last_order_time": null,
        "display_order": 3,
        "created_at": "2026-06-13T19:12:52.953Z",
        "updated_at": "2026-06-13T19:12:52.953Z",
        "updated_by": null
      },
      {
        "id": "0835943c-f966-4101-b0cc-9cdd76c577ab",
        "service_type": "takeaway",
        "day_of_week": 1,
        "slot_number": 1,
        "open_time": "12:00:00",
        "close_time": "21:45:00",
        "is_closed": false,
        "min_lead_time_minutes": 15,
        "max_preorder_days": 7,
        "last_order_time": null,
        "display_order": 4,
        "created_at": "2026-06-13T19:12:52.953Z",
        "updated_at": "2026-06-13T19:12:52.953Z",
        "updated_by": null
      },
      {
        "id": "47e66620-e77e-4a69-919b-aed080698172",
        "service_type": "dine_in",
        "day_of_week": 2,
        "slot_number": 1,
        "open_time": "12:00:00",
        "close_time": "22:00:00",
        "is_closed": false,
        "min_lead_time_minutes": 0,
        "max_preorder_days": 0,
        "last_order_time": null,
        "display_order": 1,
        "created_at": "2026-06-13T19:12:52.953Z",
        "updated_at": "2026-06-13T19:12:52.953Z",
        "updated_by": null
      },
      {
        "id": "22a2ea02-a083-4e56-8b08-4e438f456b39",
        "service_type": "reservations",
        "day_of_week": 2,
        "slot_number": 1,
        "open_time": "12:00:00",
        "close_time": "21:00:00",
        "is_closed": false,
        "min_lead_time_minutes": 30,
        "max_preorder_days": 30,
        "last_order_time": null,
        "display_order": 2,
        "created_at": "2026-06-13T19:12:52.953Z",
        "updated_at": "2026-06-13T19:12:52.953Z",
        "updated_by": null
      },
      {
        "id": "a0e3a8f9-684f-46f5-b605-0ff1700b318b",
        "service_type": "delivery",
        "day_of_week": 2,
        "slot_number": 1,
        "open_time": "12:00:00",
        "close_time": "21:30:00",
        "is_closed": false,
        "min_lead_time_minutes": 45,
        "max_preorder_days": 7,
        "last_order_time": null,
        "display_order": 3,
        "created_at": "2026-06-13T19:12:52.953Z",
        "updated_at": "2026-06-13T19:12:52.953Z",
        "updated_by": null
      },
      {
        "id": "ca71d3b2-1cc1-48aa-b11e-dbcaf375dca9",
        "service_type": "takeaway",
        "day_of_week": 2,
        "slot_number": 1,
        "open_time": "12:00:00",
        "close_time": "21:45:00",
        "is_closed": false,
        "min_lead_time_minutes": 15,
        "max_preorder_days": 7,
        "last_order_time": null,
        "display_order": 4,
        "created_at": "2026-06-13T19:12:52.953Z",
        "updated_at": "2026-06-13T19:12:52.953Z",
        "updated_by": null
      },
      {
        "id": "4c9a5692-3c37-49bd-bb4d-31d1509e30f4",
        "service_type": "dine_in",
        "day_of_week": 3,
        "slot_number": 1,
        "open_time": "12:00:00",
        "close_time": "22:00:00",
        "is_closed": false,
        "min_lead_time_minutes": 0,
        "max_preorder_days": 0,
        "last_order_time": null,
        "display_order": 1,
        "created_at": "2026-06-13T19:12:52.953Z",
        "updated_at": "2026-06-13T19:12:52.953Z",
        "updated_by": null
      },
      {
        "id": "a25a3293-a62b-474d-8aef-87803dcd2895",
        "service_type": "reservations",
        "day_of_week": 3,
        "slot_number": 1,
        "open_time": "12:00:00",
        "close_time": "21:00:00",
        "is_closed": false,
        "min_lead_time_minutes": 30,
        "max_preorder_days": 30,
        "last_order_time": null,
        "display_order": 2,
        "created_at": "2026-06-13T19:12:52.953Z",
        "updated_at": "2026-06-13T19:12:52.953Z",
        "updated_by": null
      },
      {
        "id": "2741a749-a9da-43f3-85fe-3d019cdac09b",
        "service_type": "delivery",
        "day_of_week": 3,
        "slot_number": 1,
        "open_time": "12:00:00",
        "close_time": "21:30:00",
        "is_closed": false,
        "min_lead_time_minutes": 45,
        "max_preorder_days": 7,
        "last_order_time": null,
        "display_order": 3,
        "created_at": "2026-06-13T19:12:52.953Z",
        "updated_at": "2026-06-13T19:12:52.953Z",
        "updated_by": null
      },
      {
        "id": "4a757b1d-2fa7-415c-8424-bc35c4a2f9ae",
        "service_type": "takeaway",
        "day_of_week": 3,
        "slot_number": 1,
        "open_time": "12:00:00",
        "close_time": "21:45:00",
        "is_closed": false,
        "min_lead_time_minutes": 15,
        "max_preorder_days": 7,
        "last_order_time": null,
        "display_order": 4,
        "created_at": "2026-06-13T19:12:52.953Z",
        "updated_at": "2026-06-13T19:12:52.953Z",
        "updated_by": null
      },
      {
        "id": "9242cfbd-983b-4536-b4be-ae717e2d48f7",
        "service_type": "dine_in",
        "day_of_week": 4,
        "slot_number": 1,
        "open_time": "12:00:00",
        "close_time": "22:00:00",
        "is_closed": false,
        "min_lead_time_minutes": 0,
        "max_preorder_days": 0,
        "last_order_time": null,
        "display_order": 1,
        "created_at": "2026-06-13T19:12:52.953Z",
        "updated_at": "2026-06-13T19:12:52.953Z",
        "updated_by": null
      },
      {
        "id": "96ed3585-02cd-4be0-b898-b0cf77ecbfe5",
        "service_type": "reservations",
        "day_of_week": 4,
        "slot_number": 1,
        "open_time": "12:00:00",
        "close_time": "21:00:00",
        "is_closed": false,
        "min_lead_time_minutes": 30,
        "max_preorder_days": 30,
        "last_order_time": null,
        "display_order": 2,
        "created_at": "2026-06-13T19:12:52.953Z",
        "updated_at": "2026-06-13T19:12:52.953Z",
        "updated_by": null
      },
      {
        "id": "8aeb5d29-0819-442c-aa01-0992a6c44e1b",
        "service_type": "delivery",
        "day_of_week": 4,
        "slot_number": 1,
        "open_time": "12:00:00",
        "close_time": "21:30:00",
        "is_closed": false,
        "min_lead_time_minutes": 45,
        "max_preorder_days": 7,
        "last_order_time": null,
        "display_order": 3,
        "created_at": "2026-06-13T19:12:52.953Z",
        "updated_at": "2026-06-13T19:12:52.953Z",
        "updated_by": null
      },
      {
        "id": "58b18bab-a279-4fe6-a789-b01a12ee3476",
        "service_type": "takeaway",
        "day_of_week": 4,
        "slot_number": 1,
        "open_time": "12:00:00",
        "close_time": "21:45:00",
        "is_closed": false,
        "min_lead_time_minutes": 15,
        "max_preorder_days": 7,
        "last_order_time": null,
        "display_order": 4,
        "created_at": "2026-06-13T19:12:52.953Z",
        "updated_at": "2026-06-13T19:12:52.953Z",
        "updated_by": null
      },
      {
        "id": "8a7a478c-2afd-4394-9280-6763928a2552",
        "service_type": "dine_in",
        "day_of_week": 5,
        "slot_number": 1,
        "open_time": "12:00:00",
        "close_time": "22:00:00",
        "is_closed": false,
        "min_lead_time_minutes": 0,
        "max_preorder_days": 0,
        "last_order_time": null,
        "display_order": 1,
        "created_at": "2026-06-13T19:12:52.953Z",
        "updated_at": "2026-06-13T19:12:52.953Z",
        "updated_by": null
      },
      {
        "id": "5556c307-7b2b-4e9c-b3d1-baa84183e3d7",
        "service_type": "reservations",
        "day_of_week": 5,
        "slot_number": 1,
        "open_time": "12:00:00",
        "close_time": "21:00:00",
        "is_closed": false,
        "min_lead_time_minutes": 30,
        "max_preorder_days": 30,
        "last_order_time": null,
        "display_order": 2,
        "created_at": "2026-06-13T19:12:52.953Z",
        "updated_at": "2026-06-13T19:12:52.953Z",
        "updated_by": null
      },
      {
        "id": "ae948cd3-f18d-4b76-989c-0e4585c18d9a",
        "service_type": "delivery",
        "day_of_week": 5,
        "slot_number": 1,
        "open_time": "12:00:00",
        "close_time": "21:30:00",
        "is_closed": false,
        "min_lead_time_minutes": 45,
        "max_preorder_days": 7,
        "last_order_time": null,
        "display_order": 3,
        "created_at": "2026-06-13T19:12:52.953Z",
        "updated_at": "2026-06-13T19:12:52.953Z",
        "updated_by": null
      },
      {
        "id": "152c4b2e-f66d-4112-8069-f95eef0a9c99",
        "service_type": "takeaway",
        "day_of_week": 5,
        "slot_number": 1,
        "open_time": "12:00:00",
        "close_time": "21:45:00",
        "is_closed": false,
        "min_lead_time_minutes": 15,
        "max_preorder_days": 7,
        "last_order_time": null,
        "display_order": 4,
        "created_at": "2026-06-13T19:12:52.953Z",
        "updated_at": "2026-06-13T19:12:52.953Z",
        "updated_by": null
      },
      {
        "id": "2d13b8be-950c-4190-aba2-7fe9d20a3d0f",
        "service_type": "dine_in",
        "day_of_week": 6,
        "slot_number": 1,
        "open_time": "12:00:00",
        "close_time": "22:00:00",
        "is_closed": false,
        "min_lead_time_minutes": 0,
        "max_preorder_days": 0,
        "last_order_time": null,
        "display_order": 1,
        "created_at": "2026-06-13T19:12:52.953Z",
        "updated_at": "2026-06-13T19:12:52.953Z",
        "updated_by": null
      },
      {
        "id": "b1004105-1166-45da-9f52-faabe333326b",
        "service_type": "reservations",
        "day_of_week": 6,
        "slot_number": 1,
        "open_time": "12:00:00",
        "close_time": "21:00:00",
        "is_closed": false,
        "min_lead_time_minutes": 30,
        "max_preorder_days": 30,
        "last_order_time": null,
        "display_order": 2,
        "created_at": "2026-06-13T19:12:52.953Z",
        "updated_at": "2026-06-13T19:12:52.953Z",
        "updated_by": null
      },
      {
        "id": "95a21bbe-4c1b-4cec-b1b4-d37a2dde1cc9",
        "service_type": "delivery",
        "day_of_week": 6,
        "slot_number": 1,
        "open_time": "12:00:00",
        "close_time": "21:30:00",
        "is_closed": false,
        "min_lead_time_minutes": 45,
        "max_preorder_days": 7,
        "last_order_time": null,
        "display_order": 3,
        "created_at": "2026-06-13T19:12:52.953Z",
        "updated_at": "2026-06-13T19:12:52.953Z",
        "updated_by": null
      },
      {
        "id": "253c27ef-31dc-4531-9469-de82b8793976",
        "service_type": "takeaway",
        "day_of_week": 6,
        "slot_number": 1,
        "open_time": "12:00:00",
        "close_time": "21:45:00",
        "is_closed": false,
        "min_lead_time_minutes": 15,
        "max_preorder_days": 7,
        "last_order_time": null,
        "display_order": 4,
        "created_at": "2026-06-13T19:12:52.953Z",
        "updated_at": "2026-06-13T19:12:52.953Z",
        "updated_by": null
      },
      {
        "id": "9012527f-0757-449b-856c-7909f01862e5",
        "service_type": "dine_in",
        "day_of_week": 1,
        "slot_number": 1,
        "open_time": "12:00:00",
        "close_time": "22:00:00",
        "is_closed": false,
        "min_lead_time_minutes": 0,
        "max_preorder_days": 0,
        "last_order_time": null,
        "display_order": 1,
        "created_at": "2026-06-13T19:12:56.445Z",
        "updated_at": "2026-06-13T19:12:56.445Z",
        "updated_by": null
      }
    ],
    "holiday_closures": [],
    "operational_status": [
      {
        "id": "fea557b7-a1ad-489e-86bd-1d0218bde7b5",
        "delivery_enabled": true,
        "takeaway_enabled": true,
        "reservations_enabled": true,
        "dine_in_status": "open",
        "kitchen_busy_mode": false,
        "temporary_message_pl": null,
        "temporary_message_en": null,
        "estimated_delay_minutes": 0,
        "updated_at": "2026-06-13T19:12:52.953Z",
        "updated_by": null
      }
    ],
    "system_settings": [
      {
        "key": "restaurant_address",
        "value": "Warszawska 1/3, 06-400 Ciechanów, Poland",
        "description": "The physical address of the restaurant",
        "updated_by": null,
        "updated_at": "2026-06-13T19:12:52.953Z"
      },
      {
        "key": "restaurant_phone",
        "value": "511984331",
        "description": "The public contact phone number",
        "updated_by": null,
        "updated_at": "2026-06-13T19:12:52.953Z"
      },
      {
        "key": "timezone",
        "value": "Europe/Warsaw",
        "description": "The local timezone of the restaurant",
        "updated_by": null,
        "updated_at": "2026-06-13T19:12:52.953Z"
      },
      {
        "key": "site_url",
        "value": "http://localhost:3000",
        "description": "The site URL placeholder",
        "updated_by": null,
        "updated_at": "2026-06-13T19:12:52.953Z"
      },
      {
        "key": "coordinates",
        "value": {
          "status": "unverified",
          "latitude": null,
          "longitude": null
        },
        "description": "Verified coordinates of the restaurant (coordinates status: unverified)",
        "updated_by": null,
        "updated_at": "2026-06-13T19:12:52.953Z"
      },
      {
        "key": "opening_status",
        "value": {
          "is_open": true,
          "message": null
        },
        "description": "Current public opening status banner",
        "updated_by": null,
        "updated_at": "2026-06-13T19:12:52.953Z"
      },
      {
        "key": "public_messages",
        "value": {
          "alert_banner": null,
          "welcome_message": "Welcome to Namaste Indian Restaurant!"
        },
        "description": "Public message configurations",
        "updated_by": null,
        "updated_at": "2026-06-13T19:12:52.953Z"
      },
      {
        "key": "public_service_hours",
        "value": {
          "dine_in": "12:00 - 22:00",
          "delivery": "12:00 - 21:30"
        },
        "description": "Publicly displayed opening hours summary",
        "updated_by": null,
        "updated_at": "2026-06-13T19:12:52.953Z"
      }
    ],
    "contact_inquiries": [],
    "site_content": [],
    "media_assets": [],
    "delivery_zones": [],
    "delivery_postal_codes": [],
    "delivery_fee_rules": [
      {
        "id": "ff70376c-3cf4-4e17-b61d-9bba4c652de0",
        "name": "Zone 1 (Close)",
        "min_distance_km": "0.00",
        "max_distance_km": "2.00",
        "fee_amount": "5.00",
        "rule_action": "allow",
        "message_pl": "Dostawa blisko (0-2 km)",
        "message_en": "Delivery close (0-2 km)",
        "is_active": true,
        "display_order": 1,
        "created_at": "2026-06-13T19:12:52.953Z",
        "updated_at": "2026-06-13T19:12:52.953Z",
        "updated_by": null
      },
      {
        "id": "d105933a-6413-4287-ac84-a59cbc285e2e",
        "name": "Zone 2 (Medium)",
        "min_distance_km": "2.00",
        "max_distance_km": "5.00",
        "fee_amount": "10.00",
        "rule_action": "allow",
        "message_pl": "Dostawa średnia (2-5 km)",
        "message_en": "Delivery medium (2-5 km)",
        "is_active": true,
        "display_order": 2,
        "created_at": "2026-06-13T19:12:52.953Z",
        "updated_at": "2026-06-13T19:12:52.953Z",
        "updated_by": null
      },
      {
        "id": "5784c66f-4e8f-43f8-b0af-90d265882b25",
        "name": "Zone 3 (Far)",
        "min_distance_km": "5.00",
        "max_distance_km": "20.00",
        "fee_amount": "15.00",
        "rule_action": "allow",
        "message_pl": "Dostawa daleko (5-20 km)",
        "message_en": "Delivery far (5-20 km)",
        "is_active": true,
        "display_order": 3,
        "created_at": "2026-06-13T19:12:52.953Z",
        "updated_at": "2026-06-13T19:12:52.953Z",
        "updated_by": null
      },
      {
        "id": "b6da1d21-57eb-4ab6-ac88-49cee81167e7",
        "name": "Zone 4 (Too Far)",
        "min_distance_km": "20.00",
        "max_distance_km": null,
        "fee_amount": "0.00",
        "rule_action": "contact_restaurant",
        "message_pl": "Dostawa powyżej 20 km - prosimy o kontakt",
        "message_en": "Delivery above 20 km - please contact restaurant",
        "is_active": true,
        "display_order": 4,
        "created_at": "2026-06-13T19:12:52.953Z",
        "updated_at": "2026-06-13T19:12:52.953Z",
        "updated_by": null
      }
    ],
    "packaging_fee_rules": [
      {
        "id": "2f61fd0f-cad2-4d83-83a8-4f7d993f9874",
        "name_pl": "Pojemnik na jedzenie",
        "name_en": "Food container",
        "fee_type": "food_container",
        "amount": "1.50",
        "applies_to_delivery": true,
        "applies_to_takeaway": true,
        "applies_to_dine_in": false,
        "is_active": true,
        "tax_behavior": "inclusive",
        "effective_from": "2026-06-13T19:12:52.953Z",
        "effective_to": null,
        "created_at": "2026-06-13T19:12:52.953Z",
        "updated_at": "2026-06-13T19:12:52.953Z",
        "updated_by": null
      },
      {
        "id": "ea716cc6-63fb-42d0-ba40-cc8fe77ddf26",
        "name_pl": "Kubek na napój",
        "name_en": "Beverage cup",
        "fee_type": "beverage_cup",
        "amount": "1.00",
        "applies_to_delivery": true,
        "applies_to_takeaway": true,
        "applies_to_dine_in": false,
        "is_active": true,
        "tax_behavior": "inclusive",
        "effective_from": "2026-06-13T19:12:52.953Z",
        "effective_to": null,
        "created_at": "2026-06-13T19:12:52.953Z",
        "updated_at": "2026-06-13T19:12:52.953Z",
        "updated_by": null
      },
      {
        "id": "d972f311-bbc8-4cdd-82d3-d73265b04e09",
        "name_pl": "Torba papierowa",
        "name_en": "Paper bag",
        "fee_type": "bag",
        "amount": "2.00",
        "applies_to_delivery": true,
        "applies_to_takeaway": true,
        "applies_to_dine_in": false,
        "is_active": true,
        "tax_behavior": "inclusive",
        "effective_from": "2026-06-13T19:12:52.953Z",
        "effective_to": null,
        "created_at": "2026-06-13T19:12:52.953Z",
        "updated_at": "2026-06-13T19:12:52.953Z",
        "updated_by": null
      }
    ],
    "menu_item_packaging_rules": [],
    "orders": [],
    "order_status_events": [],
    "order_items": [],
    "order_charges": [],
    "notification_logs": [],
    "admin_activity_logs": []
  }
}